README.md
setup.py
partricol/__init__.py
partricol.egg-info/PKG-INFO
partricol.egg-info/SOURCES.txt
partricol.egg-info/dependency_links.txt
partricol.egg-info/top_level.txt
partricol/colibri2trilegal/__init__.py
partricol/colibri2trilegal/colibri2trilegal_cycy_eagb.py
partricol/colibri2trilegal/colibri2trilegal_cycy_noeagb.py
partricol/colibri2trilegal/colibri2trilegal_cycy_noeagb_fake.py
partricol/colibri2trilegal/colibri2trilegal_phil.py
partricol/colibri2trilegal/def_par_colibri2trilegal.py
partricol/colibri2trilegal/write_par_colibri2trilegal.py
partricol/cypar/__init__.py
partricol/cypar/cypar.py
partricol/match2trilegal/__init__.py
partricol/match2trilegal/match2trilegal.py
partricol/match2trilegal/setup.py
partricol/parcol/__init__.py
partricol/parcol/dbert_colibri_replace.py
partricol/parcol/parcol.py
partricol/parcol/revisegrid_comp.py
partricol/tripar/__init__.py
partricol/tripar/def_par_trilegal.py
partricol/tripar/read_par_trilegal.py
partricol/tripar/run_trilegal.py
partricol/tripar/write_par_trilegal.py