Metadata-Version: 2.1
Name: partricol
Version: 0.0.5.3
Summary: Package collected during my work with PARSEC-TRILEGAL-COLIBRI
Home-page: https://gitlab.com/cycyustc/partricol
Author: Yang Chen
Author-email: cycyustc@gmail.com
License: UNKNOWN
Platform: UNKNOWN
Classifier: Programming Language :: Python :: 3
Classifier: License :: OSI Approved :: MIT License
Classifier: Operating System :: OS Independent
Requires-Python: >=3.6
